{"text": " for my work \u2013 independently of some particular file. Thus I'd like to use the file as an argument. I know how to use an argument itself but have problems splitting the input after the string and concat it afterwards. If I was able to split the filename ar", "meta": {"pile_set_name": "StackExchange"}, "source_fname": "data/pile_demo.jsonl", "hash": "roi1H4EprKMMDzpUL_5jYw", "n_tokens": 54, "tokens": ["\u0120for", "\u0120my", "\u0120work", "\u0120\u00e2\u0122\u0135", "\u0120independently", "\u0120of", "\u0120some", "\u0120particular", "\u0120file", ".", "\u0120Thus", "\u0120I", "'d", "\u0120like", "\u0120to", "\u0120use", "\u0120the", "\u0120file", "\u0120as", "\u0120an", "\u0120argument", ".", "\u0120I", "\u0120know", "\u0120how", "\u0120to", "\u0120use", "\u0120an", "\u0120argument", "\u0120itself", "\u0120but", "\u0120have", "\u0120problems", "\u0120splitting", "\u0120the", "\u0120input", "\u0120after", "\u0120the", "\u0120string", "\u0120and", "\u0120conc", "at", "\u0120it", "\u0120afterwards", ".", "\u0120If", "\u0120I", "\u0120was", "\u0120able", "\u0120to", "\u0120split", "\u0120the", "\u0120filename", "\u0120ar"]}