{".class":"MypyFile","_fullname":"friendli.sdk.sync.resource.system","future_import_flags":["annotations"],"is_partial_stub_package":false,"is_stub":false,"names":{".class":"SymbolTable","ResourceBase":{".class":"SymbolTableNode","cross_ref":"friendli.sdk.sync.resource._base.ResourceBase","kind":"Gdef"},"SystemResource":{".class":"SymbolTableNode","kind":"Gdef","node":{".class":"TypeInfo","_promote":[],"abstract_attributes":[],"alt_promote":null,"bases":["friendli.sdk.sync.resource._base.ResourceBase"],"dataclass_transform_spec":null,"declared_metaclass":null,"defn":{".class":"ClassDef","fullname":"friendli.sdk.sync.resource.system.SystemResource","name":"SystemResource","type_vars":[]},"deletable_attributes":[],"flags":[],"fullname":"friendli.sdk.sync.resource.system.SystemResource","has_param_spec_type":false,"metaclass_type":null,"metadata":{},"module_name":"friendli.sdk.sync.resource.system","mro":["friendli.sdk.sync.resource.system.SystemResource","friendli.sdk.sync.resource._base.ResourceBase","builtins.object"],"names":{".class":"SymbolTable","ping":{".class":"SymbolTableNode","kind":"Mdef","node":{".class":"Decorator","func":{".class":"FuncDef","abstract_status":0,"arg_kinds":[0],"arg_names":["self"],"dataclass_transform_spec":null,"flags":["is_decorated"],"fullname":"friendli.sdk.sync.resource.system.SystemResource.ping","name":"ping","type":{".class":"CallableType","arg_kinds":[0],"arg_names":["self"],"arg_types":["friendli.sdk.sync.resource.system.SystemResource"],"bound_args":[],"def_extras":{"first_arg":"self"},"fallback":"builtins.function","from_concatenate":false,"implicit":false,"imprecise_arg_kinds":false,"is_ellipsis_args":false,"name":"ping of SystemResource","ret_type":{".class":"NoneType"},"type_guard":null,"unpack_kwargs":false,"variables":[]}},"is_overload":false,"var":{".class":"Var","flags":["is_initialized_in_class","is_ready","is_inferred"],"fullname":"friendli.sdk.sync.resource.system.SystemResource.ping","name":"ping","type":{".class":"CallableType","arg_kinds":[0],"arg_names":["self"],"arg_types":["friendli.sdk.sync.resource.system.SystemResource"],"bound_args":[],"def_extras":{},"fallback":"builtins.function","from_concatenate":false,"implicit":false,"imprecise_arg_kinds":false,"is_ellipsis_args":false,"name":"ping of SystemResource","ret_type":{".class":"NoneType"},"type_guard":null,"unpack_kwargs":false,"variables":[]}}}},"version":{".class":"SymbolTableNode","kind":"Mdef","node":{".class":"Decorator","func":{".class":"FuncDef","abstract_status":0,"arg_kinds":[0],"arg_names":["self"],"dataclass_transform_spec":null,"flags":["is_decorated"],"fullname":"friendli.sdk.sync.resource.system.SystemResource.version","name":"version","type":{".class":"CallableType","arg_kinds":[0],"arg_names":["self"],"arg_types":["friendli.sdk.sync.resource.system.SystemResource"],"bound_args":[],"def_extras":{"first_arg":"self"},"fallback":"builtins.function","from_concatenate":false,"implicit":false,"imprecise_arg_kinds":false,"is_ellipsis_args":false,"name":"version of SystemResource","ret_type":"friendli.schema.common_system.VersionResponse","type_guard":null,"unpack_kwargs":false,"variables":[]}},"is_overload":false,"var":{".class":"Var","flags":["is_initialized_in_class","is_ready","is_inferred"],"fullname":"friendli.sdk.sync.resource.system.SystemResource.version","name":"version","type":{".class":"CallableType","arg_kinds":[0],"arg_names":["self"],"arg_types":["friendli.sdk.sync.resource.system.SystemResource"],"bound_args":[],"def_extras":{},"fallback":"builtins.function","from_concatenate":false,"implicit":false,"imprecise_arg_kinds":false,"is_ellipsis_args":false,"name":"version of SystemResource","ret_type":"friendli.schema.common_system.VersionResponse","type_guard":null,"unpack_kwargs":false,"variables":[]}}}}},"self_type":{".class":"TypeVarType","default":{".class":"AnyType","missing_import_name":null,"source_any":null,"type_of_any":4},"fullname":"friendli.sdk.sync.resource.system.SystemResource.Self","id":0,"name":"Self","namespace":"","upper_bound":"friendli.sdk.sync.resource.system.SystemResource","values":[],"variance":0},"slots":null,"tuple_type":null,"type_vars":[],"typeddict_type":null}},"VersionResponse":{".class":"SymbolTableNode","cross_ref":"friendli.schema.common_system.VersionResponse","kind":"Gdef"},"__annotations__":{".class":"SymbolTableNode","kind":"Gdef","node":{".class":"Var","flags":["is_ready"],"fullname":"friendli.sdk.sync.resource.system.__annotations__","name":"__annotations__","type":{".class":"Instance","args":["builtins.str",{".class":"AnyType","missing_import_name":null,"source_any":null,"type_of_any":6}],"type_ref":"builtins.dict"}}},"__doc__":{".class":"SymbolTableNode","kind":"Gdef","node":{".class":"Var","flags":["is_ready"],"fullname":"friendli.sdk.sync.resource.system.__doc__","name":"__doc__","type":"builtins.str"}},"__file__":{".class":"SymbolTableNode","kind":"Gdef","node":{".class":"Var","flags":["is_ready"],"fullname":"friendli.sdk.sync.resource.system.__file__","name":"__file__","type":"builtins.str"}},"__name__":{".class":"SymbolTableNode","kind":"Gdef","node":{".class":"Var","flags":["is_ready"],"fullname":"friendli.sdk.sync.resource.system.__name__","name":"__name__","type":"builtins.str"}},"__package__":{".class":"SymbolTableNode","kind":"Gdef","node":{".class":"Var","flags":["is_ready"],"fullname":"friendli.sdk.sync.resource.system.__package__","name":"__package__","type":"builtins.str"}},"annotations":{".class":"SymbolTableNode","cross_ref":"__future__.annotations","kind":"Gdef"},"translate_exception":{".class":"SymbolTableNode","cross_ref":"friendli.sdk.translator.translate_exception","kind":"Gdef"}},"path":"/Users/ahnjaeshin/Desktop/fai/ws/periflow-backends/client/src/friendli/sdk/sync/resource/system.py"}