{"commitInfo":{"timestamp":1751313851232,"operation":"WRITE","operationParameters":{"mode":"Overwrite","partitionBy":"[]"},"readVersion":0,"isolationLevel":"Serializable","isBlindAppend":false,"operationMetrics":{"numFiles":"1","numRemovedFiles":"1","numRemovedBytes":"1749","numOutputRows":"4","numOutputBytes":"1749"},"engineInfo":"Apache-Spark/4.0.0 Delta-Lake/4.0.0","txnId":"4ad060cc-6259-401c-95fe-6e5be86199de"}}
{"add":{"path":"part-00000-55a8ea90-073d-49fa-a696-e1718cd76212-c000.snappy.parquet","partitionValues":{},"size":1749,"modificationTime":1751313850651,"dataChange":true,"stats":"{\"numRecords\":4,\"minValues\":{\"id\":1,\"customer_name\":\"Another Person\",\"phone\":\"555-0001\",\"total_purchases\":50.0,\"region\":\"East\"},\"maxValues\":{\"id\":4,\"customer_name\":\"Some Guy\",\"phone\":\"555-0004\",\"total_purchases\":200.25,\"region\":\"West\"},\"nullCount\":{\"id\":0,\"customer_name\":0,\"phone\":0,\"total_purchases\":0,\"region\":0}}"}}
{"remove":{"path":"part-00000-0e96d8da-f176-4411-81b9-b7ecc49634d0-c000.snappy.parquet","deletionTimestamp":1751313851205,"dataChange":true,"extendedFileMetadata":true,"partitionValues":{},"size":1749}}
